django_graph-1.2.dist-info/METADATA
django_graph-1.2.dist-info/RECORD
django_graph-1.2.dist-info/WHEEL
django_graph-1.2.dist-info/top_level.txt
graph/__init__.py
graph/admin.py
graph/apps.py
graph/models.py
graph/serializers.py
graph/tests.py
graph/urls.py
graph/views.py
