Metadata-Version: 2.1
Name: django-graph
Version: 1.2
Summary: a django application based on openfalcon
Home-page: https://www.python.org
Author: brad
Author-email: xiaoleluo@126.com
License: UNKNOWN
Platform: UNKNOWN
